pyirr/IRR_result.py
pyirr/N2_cohen_kappa.py
pyirr/N_cohen_kappa.py
pyirr/__init__.py
pyirr/agree.py
pyirr/bhapkar.py
pyirr/finn.py
pyirr/intraclass_correlation.py
pyirr/iota.py
pyirr/kappa2.py
pyirr/kappam_fleiss.py
pyirr/kappam_light.py
pyirr/kendall.py
pyirr/kripp_alpha.py
pyirr/maxwell.py
pyirr/meancor.py
pyirr/meanrho.py
pyirr/rater_bias.py
pyirr/read_data.py
pyirr/rel_inter_intra.py
pyirr/robinson.py
pyirr/stuart_maxwell_mh.py
pyirr/data/anxiety.csv
pyirr/data/diagnoses.csv
pyirr/data/gonio.csv
pyirr/data/nmm.csv
pyirr/data/photo.p
pyirr/data/video.csv
pyirr/data/vision.csv
pyirr-0.84.1.2.dist-info/LICENSE
pyirr-0.84.1.2.dist-info/METADATA
pyirr-0.84.1.2.dist-info/WHEEL
pyirr-0.84.1.2.dist-info/top_level.txt
pyirr-0.84.1.2.dist-info/RECORD
