Metadata-Version: 2.1
Name: pyirr
Version: 0.84.1.2
Summary: Python implementation of the R package IRR
Home-page: https://github.com/rickdkk/pyirr
Download-URL: https://github.com/rickdkk/pyirr
Author: Rick de Klerk
Author-email: rickdkk@gmail.com
License: GNU GPLv3
Keywords: statistics
Platform: UNKNOWN
License-File: LICENSE
Requires-Dist: numpy
Requires-Dist: scipy
Requires-Dist: pandas
Requires-Dist: statsmodels
